h265_compress/__init__.py
h265_compress/compress.py
h265_compress-0.1.dist-info/LICENSE
h265_compress-0.1.dist-info/METADATA
h265_compress-0.1.dist-info/WHEEL
h265_compress-0.1.dist-info/top_level.txt
h265_compress-0.1.dist-info/RECORD
