Metadata-Version: 2.1
Name: h265_compress
Version: 0.1
Summary: A Python library to compress YUV files to H.265 MP4.
Author: Minghao Liu
Author-email: minghao13187@gmail.com
License: MIT
Classifier: Programming Language :: Python :: 3
Classifier: License :: OSI Approved :: MIT License
Classifier: Operating System :: OS Independent
License-File: LICENSE
Requires-Dist: ffmpeg-python
